LICENSE
README.md
__init__.py
hbsst.py
pyproject.toml
setup.cfg
hbsst.egg-info/PKG-INFO
hbsst.egg-info/SOURCES.txt
hbsst.egg-info/dependency_links.txt
hbsst.egg-info/top_level.txt
hbsst-1.0.2.dist-info/LICENSE
hbsst-1.0.2.dist-info/METADATA
hbsst-1.0.2.dist-info/WHEEL
hbsst-1.0.2.dist-info/top_level.txt
hbsst-1.0.2.dist-info/RECORD
