Metadata-Version: 2.1
Name: hbsst
Version: 1.0.2
Summary: This tool integrates and optimizes the commands submitted by Baidu webmaster API, and changes them into user-friendly Python functions to facilitate program calls.
Home-page: https://github.com/hestudio-community/hbsst
Author: heStudio
Author-email: heStudio <hestudio@hestudio.net>
Project-URL: Homepage, https://github.com/hestudio-community/hbsst
Project-URL: Bug Tracker, https://github.com/hestudio-community/hbsst/issues
Project-URL: Blog, https://www.hestudio.net/
Classifier: Programming Language :: Python :: 3
Classifier: License :: OSI Approved :: GNU Affero General Public License v3 or later (AGPLv3+)
Classifier: Natural Language :: Chinese (Simplified)
Classifier: Operating System :: POSIX :: Linux
Classifier: Topic :: System :: Operating System Kernels :: Linux
Requires-Python: >=3.6
License-File: LICENSE
